tinyflux/__init__.py
tinyflux/database.py
tinyflux/decorators.py
tinyflux/index.py
tinyflux/measurement.py
tinyflux/point.py
tinyflux/py.typed
tinyflux/queries.py
tinyflux/storages.py
tinyflux/utils.py
tinyflux/version.py
tinyflux-1.2.0.dist-info/licenses/LICENSE
tinyflux-1.2.0.dist-info/METADATA
tinyflux-1.2.0.dist-info/WHEEL
tinyflux-1.2.0.dist-info/top_level.txt
tinyflux-1.2.0.dist-info/RECORD
